ckanext/ssm/__init__.py
ckanext/ssm/config_declaration.yaml
ckanext/ssm/plugin.py
ckanext/ssm/tests/test_plugin.py
ckanext_ssm_config-0.1.1.dist-info/licenses/LICENSE
test/features/environment.py
test/features/steps/steps.py
ckanext_ssm_config-0.1.1.dist-info/METADATA
ckanext_ssm_config-0.1.1.dist-info/WHEEL
ckanext_ssm_config-0.1.1.dist-info/entry_points.txt
ckanext_ssm_config-0.1.1.dist-info/top_level.txt
ckanext_ssm_config-0.1.1.dist-info/RECORD
