Metadata-Version: 2.4
Name: ckanext-ssm-config
Version: 0.1.1
Summary: Imports Amazon SSM Parameter Store values into CKAN config
Author-email: ThrawnCA <carl.antuar@smartservice.qld.gov.au>, Queensland Online <qol.development@smartservice.qld.gov.au>, "William Dutton (duttonw)" <william.dutton@qld.gov.au>
Maintainer-email: ThrawnCA <carl.antuar@smartservice.qld.gov.au>, Queensland Online <qol.development@smartservice.qld.gov.au>, "William Dutton (duttonw)" <william.dutton@qld.gov.au>
License: AGPL
Project-URL: Homepage, https://github.com/qld-gov-au/ckanext-ssm-config
Keywords: CKAN,extension,aws param store,aws,param store
Classifier: Development Status :: 5 - Production/Stable
Classifier: License :: OSI Approved :: GNU Affero General Public License v3 or later (AGPLv3+)
Classifier: Programming Language :: Python :: 3.9
Classifier: Programming Language :: Python :: 3.10
License-File: LICENSE
Requires-Dist: typing_extensions
Requires-Dist: boto3>=1.4.4
Requires-Dist: types-boto3[ssm]>=1.37.34
Requires-Dist: six>=1.11.0
Provides-Extra: test
Requires-Dist: pytest-factoryboy; extra == "test"
Dynamic: license-file
